glow/__init__.py
glow/colors.py
glow/configs.py
glow/constants.py
glow/glowhub.py
glow/logics.py
glow/manage.py
glow/printout.py
glow/secrets.py
glow/bin/glow.py
glow/llm/__init__.py
glow/llm/anthropic.py
glow/llm/base.py
glow/llm/gemini.py
glow/llm/openai.py
glow/llm/run.py
glow/utils/command.py
glow/utils/dotenv.py
glow/utils/yaml.py
glow_cli-0.3.7.dist-info/METADATA
glow_cli-0.3.7.dist-info/WHEEL
glow_cli-0.3.7.dist-info/entry_points.txt
glow_cli-0.3.7.dist-info/top_level.txt
glow_cli-0.3.7.dist-info/RECORD
