Metadata-Version: 2.4
Name: glow-cli
Version: 0.3.7
Summary: Smart CLI tool for shell template
Author-email: "Xiaochen Zhang (Ray)" <ray@fireworkhq.com>
Project-URL: homepage, https://github.com/loopsocial/glow
Project-URL: repository, https://github.com/loopsocial/glow
Keywords: smart cli,shell template
Classifier: Development Status :: 2 - Pre-Alpha
Classifier: Intended Audience :: End Users/Desktop
Classifier: License :: OSI Approved :: GNU General Public License v3 (GPLv3)
Classifier: Programming Language :: Python :: 3.8
Classifier: Programming Language :: Python :: 3.9
Classifier: Programming Language :: Python :: 3.10
Classifier: Programming Language :: Python :: 3.11
Classifier: Programming Language :: Python :: 3.12
Requires-Dist: python-dotenv
Requires-Dist: pyyaml
Requires-Dist: fire
Requires-Dist: requests
